acquifer/__init__.py
acquifer/metadata.py
acquifer/scripts.py
acquifer/tcpip.py
acquifer/test.py
acquifer/utils.py
acquifer/version.py
acquifer/dlls/BitMiracle.LibTiff.NET.dll
acquifer/dlls/BitMiracle.LibTiff.NET.xml
acquifer/dlls/Microsoft.Extensions.Primitives.dll
acquifer/dlls/Microsoft.Extensions.Primitives.xml
acquifer/dlls/PlateViewer.Common.BaseFunctionality.dll
acquifer/dlls/PlateViewer.TifLoader.dll
acquifer/dlls/ScriptUtils.dll
acquifer/dlls/ScriptUtils.dll.config
acquifer/dlls/System.Buffers.dll
acquifer/dlls/System.Buffers.xml
acquifer/dlls/System.Memory.dll
acquifer/dlls/System.Memory.xml
acquifer/dlls/System.Numerics.Vectors.dll
acquifer/dlls/System.Numerics.Vectors.xml
acquifer/dlls/System.Runtime.CompilerServices.Unsafe.dll
acquifer/dlls/System.Runtime.CompilerServices.Unsafe.xml
acquifer-2.0.0.dist-info/METADATA
acquifer-2.0.0.dist-info/WHEEL
acquifer-2.0.0.dist-info/licenses/LICENSE
acquifer-2.0.0.dist-info/RECORD
