Metadata-Version: 2.1
Name: acquifer
Version: 2.0.0
Summary: Utilitary functions when working with image datasets acquired with an ACQUIFER Imaging Machine microscope
Project-URL: Homepage, https://acquifer.de
Project-URL: Repository, https://github.com/acquifer/Acquifer-Python-API
Project-URL: Bug Tracker, https://github.com/acquifer/Acquifer-Python-API/issues
Project-URL: Twitter, https://twitter.com/myacquifer
Author: Laurent Thomas
License-File: LICENSE
Keywords: image-analysis,image-processing,microscopy,smart-imaging
Classifier: Intended Audience :: Science/Research
Classifier: License :: OSI Approved :: GNU General Public License v3 (GPLv3)
Classifier: Operating System :: OS Independent
Classifier: Programming Language :: Python :: 3
Requires-Python: >=3.7
Requires-Dist: numpy
Requires-Dist: pythonnet
